.DS_Store
LICENSE
MANIFEST.in
README.md
setup.py
dist/.DS_Store
dist/xss_hmm_detect-0.0.1.tar.gz
xss_hmm_detect/.DS_Store
xss_hmm_detect/__init__.py
xss_hmm_detect/hmm-xss-train.pkl
xss_hmm_detect.egg-info/PKG-INFO
xss_hmm_detect.egg-info/SOURCES.txt
xss_hmm_detect.egg-info/dependency_links.txt
xss_hmm_detect.egg-info/top_level.txt